sauce_storage_api/__init__.py
sauce_storage_api/sauce_storage_api.py
sauce_storage_api-1.0.3.dist-info/METADATA
sauce_storage_api-1.0.3.dist-info/WHEEL
sauce_storage_api-1.0.3.dist-info/top_level.txt
sauce_storage_api-1.0.3.dist-info/RECORD
