Metadata-Version: 2.1
Name: sauce-storage-api
Version: 1.0.3
Summary: Lib to use saucelabs Application Storage API - https://wiki.saucelabs.com/display/DOCS/Application+Storage
Home-page: https://github.com/avilela/SauceLabsApplicationStorageApi
Author: Augusto Vilela
Author-email: avilelateixeira@gmail.com
License: UNKNOWN
Platform: UNKNOWN
Requires-Python: >=3.6
Requires-Dist: requests
